{
  "updated_at": "2026-07-24T14:50:22.449499+09:00",
  "workers": {
    "Notion Sync": {
      "worker": "Notion Sync",
      "status": "skipped",
      "items": null,
      "detail": "NOTION_API_KEY/DB 미설정",
      "duration_ms": 0,
      "last_run": "2026-07-22T03:25:24.981022+09:00"
    },
    "Data Officer": {
      "worker": "Data Officer",
      "last_run": "2026-07-24T14:50:04.702393+09:00",
      "status": "completed",
      "items": 22,
      "duration_ms": 14263
    },
    "News Research": {
      "worker": "News Research",
      "last_run": "2026-07-24T14:50:18.967059+09:00",
      "status": "completed",
      "items": 180,
      "duration_ms": 3455
    },
    "Theme Analyst": {
      "worker": "Theme Analyst",
      "last_run": "2026-07-24T07:29:39.774213+09:00",
      "status": "completed",
      "items": 3,
      "duration_ms": 2
    },
    "Trade Manager": {
      "worker": "Trade Manager",
      "last_run": "2026-07-24T06:04:00.797659+09:00",
      "status": "completed",
      "items": 35,
      "duration_ms": 4
    },
    "Publisher": {
      "worker": "Publisher",
      "status": "completed",
      "items": 3,
      "detail": "pages + static",
      "duration_ms": 0,
      "last_run": "2026-07-24T14:50:22.449386+09:00"
    },
    "TA Analyst": {
      "worker": "TA Analyst",
      "last_run": "2026-07-24T07:29:39.781368+09:00",
      "status": "completed",
      "items": 120,
      "duration_ms": 84
    },
    "Macro FRED": {
      "worker": "Macro FRED",
      "last_run": "2026-07-24T14:11:22.823068+09:00",
      "status": "completed",
      "items": 5,
      "duration_ms": 0
    },
    "Macro ECOS": {
      "worker": "Macro ECOS",
      "last_run": "2026-07-24T14:11:22.823158+09:00",
      "status": "completed",
      "items": null,
      "duration_ms": 0
    },
    "Macro Upbit": {
      "worker": "Macro Upbit",
      "last_run": "2026-07-24T14:11:22.823173+09:00",
      "status": "completed",
      "items": 3,
      "duration_ms": 748
    },
    "Stock KR Ranking": {
      "worker": "Stock KR Ranking",
      "last_run": "2026-07-24T14:49:07.513866+09:00",
      "status": "completed",
      "items": 2872,
      "duration_ms": 1492
    },
    "Stock US Ranking": {
      "worker": "Stock US Ranking",
      "last_run": "2026-07-24T14:49:09.007708+09:00",
      "status": "completed",
      "items": 503,
      "duration_ms": 54230
    },
    "Stock Hub 보조시세": {
      "worker": "Stock Hub 보조시세",
      "last_run": "2026-07-24T14:50:03.242350+09:00",
      "status": "completed",
      "items": 2,
      "duration_ms": 1423
    },
    "FS DART corpCode": {
      "worker": "FS DART corpCode",
      "last_run": "2026-07-24T07:10:33.598775+09:00",
      "status": "completed",
      "items": null,
      "duration_ms": 0
    },
    "FS EDGAR CIK맵": {
      "worker": "FS EDGAR CIK맵",
      "last_run": "2026-07-24T07:10:33.610750+09:00",
      "status": "completed",
      "items": null,
      "duration_ms": 173
    },
    "Asset Kiwoom": {
      "worker": "Asset Kiwoom",
      "last_run": "2026-07-24T07:31:23.844278+09:00",
      "status": "completed",
      "items": null,
      "duration_ms": 3
    },
    "Asset KIS 위탁": {
      "worker": "Asset KIS 위탁",
      "last_run": "2026-07-24T07:31:23.849879+09:00",
      "status": "completed",
      "items": null,
      "duration_ms": 0
    },
    "Asset KIS ISA": {
      "worker": "Asset KIS ISA",
      "last_run": "2026-07-24T07:31:23.849893+09:00",
      "status": "completed",
      "items": null,
      "duration_ms": 0
    },
    "Asset BYBIT": {
      "worker": "Asset BYBIT",
      "last_run": "2026-07-24T07:31:23.849900+09:00",
      "status": "completed",
      "items": null,
      "duration_ms": 0
    },
    "Vault Sync": {
      "worker": "Vault Sync",
      "status": "skipped",
      "items": null,
      "detail": "TH_DATA/00_Watchlist 없음/비어있음",
      "duration_ms": 0,
      "last_run": "2026-07-24T14:49:07.481938+09:00"
    },
    "Vault Journal": {
      "worker": "Vault Journal",
      "status": "completed",
      "items": 1,
      "detail": "10_Journal/ write-back",
      "duration_ms": 0,
      "last_run": "2026-07-24T13:50:56.179131+09:00"
    }
  }
}