{
  "code": "MU",
  "name": "Micron Technology",
  "market": "US",
  "as_of": "2026-07-21T16:13:26.901292+00:00",
  "source": "edgar",
  "growth": {
    "latest_year": "2025",
    "value": 48.85,
    "cagr_pct": 6.71,
    "judgment": "good",
    "series": [
      {
        "year": "2021",
        "value": 27705000000
      },
      {
        "year": "2022",
        "value": 30758000000
      },
      {
        "year": "2023",
        "value": 15540000000
      },
      {
        "year": "2024",
        "value": 25111000000
      },
      {
        "year": "2025",
        "value": 37378000000
      }
    ]
  },
  "profitability": {
    "latest_year": "2025",
    "value": 26.14,
    "own_5y_avg": 19.15,
    "judgment": "good",
    "series": [
      {
        "year": "2021",
        "value": 22.68
      },
      {
        "year": "2022",
        "value": 31.54
      },
      {
        "year": "2023",
        "value": -36.97
      },
      {
        "year": "2024",
        "value": 5.19
      },
      {
        "year": "2025",
        "value": 26.14
      }
    ]
  },
  "stability": {
    "latest_year": "2025",
    "value": 52.86,
    "judgment": "good",
    "series": [
      {
        "year": "2021",
        "value": 33.95
      },
      {
        "year": "2022",
        "value": 32.81
      },
      {
        "year": "2023",
        "value": 45.63
      },
      {
        "year": "2024",
        "value": 53.81
      },
      {
        "year": "2025",
        "value": 52.86
      }
    ]
  },
  "cashflow": {
    "latest_year": "2025",
    "value": 1668000000,
    "judgment": "neutral",
    "series": [
      {
        "year": "2016",
        "value": -2649000000
      },
      {
        "year": "2017",
        "value": 3419000000
      },
      {
        "year": "2018",
        "value": 8521000000
      },
      {
        "year": "2019",
        "value": 3409000000
      },
      {
        "year": "2020",
        "value": 83000000
      },
      {
        "year": "2021",
        "value": 2438000000
      },
      {
        "year": "2022",
        "value": 3114000000
      },
      {
        "year": "2023",
        "value": -6117000000
      },
      {
        "year": "2024",
        "value": 121000000
      },
      {
        "year": "2025",
        "value": 1668000000
      }
    ]
  },
  "valuation": {
    "latest_year": "2025",
    "eps": 7.59,
    "per": 127.52,
    "note": null
  }
}